azure/mgmt/webpubsub/__init__.py
azure/mgmt/webpubsub/_configuration.py
azure/mgmt/webpubsub/_patch.py
azure/mgmt/webpubsub/_serialization.py
azure/mgmt/webpubsub/_version.py
azure/mgmt/webpubsub/_web_pub_sub_management_client.py
azure/mgmt/webpubsub/py.typed
azure/mgmt/webpubsub/aio/__init__.py
azure/mgmt/webpubsub/aio/_configuration.py
azure/mgmt/webpubsub/aio/_patch.py
azure/mgmt/webpubsub/aio/_web_pub_sub_management_client.py
azure/mgmt/webpubsub/aio/operations/__init__.py
azure/mgmt/webpubsub/aio/operations/_operations.py
azure/mgmt/webpubsub/aio/operations/_patch.py
azure/mgmt/webpubsub/aio/operations/_usages_operations.py
azure/mgmt/webpubsub/aio/operations/_web_pub_sub_custom_certificates_operations.py
azure/mgmt/webpubsub/aio/operations/_web_pub_sub_custom_domains_operations.py
azure/mgmt/webpubsub/aio/operations/_web_pub_sub_hubs_operations.py
azure/mgmt/webpubsub/aio/operations/_web_pub_sub_operations.py
azure/mgmt/webpubsub/aio/operations/_web_pub_sub_private_endpoint_connections_operations.py
azure/mgmt/webpubsub/aio/operations/_web_pub_sub_private_link_resources_operations.py
azure/mgmt/webpubsub/aio/operations/_web_pub_sub_replica_shared_private_link_resources_operations.py
azure/mgmt/webpubsub/aio/operations/_web_pub_sub_replicas_operations.py
azure/mgmt/webpubsub/aio/operations/_web_pub_sub_shared_private_link_resources_operations.py
azure/mgmt/webpubsub/models/__init__.py
azure/mgmt/webpubsub/models/_models_py3.py
azure/mgmt/webpubsub/models/_patch.py
azure/mgmt/webpubsub/models/_web_pub_sub_management_client_enums.py
azure/mgmt/webpubsub/operations/__init__.py
azure/mgmt/webpubsub/operations/_operations.py
azure/mgmt/webpubsub/operations/_patch.py
azure/mgmt/webpubsub/operations/_usages_operations.py
azure/mgmt/webpubsub/operations/_web_pub_sub_custom_certificates_operations.py
azure/mgmt/webpubsub/operations/_web_pub_sub_custom_domains_operations.py
azure/mgmt/webpubsub/operations/_web_pub_sub_hubs_operations.py
azure_mgmt_webpubsub-2.0.0.dist-info/LICENSE
azure_mgmt_webpubsub-2.0.0.dist-info/METADATA
azure_mgmt_webpubsub-2.0.0.dist-info/WHEEL
azure_mgmt_webpubsub-2.0.0.dist-info/top_level.txt
azure_mgmt_webpubsub-2.0.0.dist-info/RECORD
